tts/TTS.py
tts/__init__.py
brnow_tts-0.1.0.dist-info/LICENSE
brnow_tts-0.1.0.dist-info/METADATA
brnow_tts-0.1.0.dist-info/WHEEL
brnow_tts-0.1.0.dist-info/top_level.txt
brnow_tts-0.1.0.dist-info/RECORD
